Metadata-Version: 1.0
Name: tfmpl
Version: 1.0.2
Summary: Seamlessly integrate matplotlib figures tensorflow summaries.
Home-page: https://github.com/cheind/tf-matplotlib
Author: Christoph Heindl
Author-email: UNKNOWN
License: MIT
Keywords: tensorflow matplotlib tensorboard
Platform: UNKNOWN
